importmem/__init__.py
importmem/cli.py
importmem-0.1.0.dist-info/LICENSE
importmem-0.1.0.dist-info/METADATA
importmem-0.1.0.dist-info/WHEEL
importmem-0.1.0.dist-info/entry_points.txt
importmem-0.1.0.dist-info/top_level.txt
importmem-0.1.0.dist-info/RECORD
